package/__init__.py
package/main.py
thisisjustanotherpackage-0.0.5.dist-info/LICENSE
thisisjustanotherpackage-0.0.5.dist-info/METADATA
thisisjustanotherpackage-0.0.5.dist-info/WHEEL
thisisjustanotherpackage-0.0.5.dist-info/top_level.txt
thisisjustanotherpackage-0.0.5.dist-info/RECORD
