Metadata-Version: 2.1
Name: thisisjustanotherpackage
Version: 0.0.5
Summary: this is just another package
Home-page: UNKNOWN
Author: thisisjust
Author-email: this@is.just
License: UNKNOWN
Platform: UNKNOWN
Requires-Dist: urllib3 (==1.25.11)
